torch_frame/__init__.py
torch_frame/_stype.py
torch_frame/typing.py
torch_frame/config/__init__.py
torch_frame/config/image_embedder.py
torch_frame/config/model.py
torch_frame/config/text_embedder.py
torch_frame/config/text_tokenizer.py
torch_frame/data/__init__.py
torch_frame/data/dataset.py
torch_frame/data/download.py
torch_frame/data/loader.py
torch_frame/data/mapper.py
torch_frame/data/multi_embedding_tensor.py
torch_frame/data/multi_nested_tensor.py
torch_frame/data/multi_tensor.py
torch_frame/data/stats.py
torch_frame/data/tensor_frame.py
torch_frame/datasets/__init__.py
torch_frame/datasets/adult_census_income.py
torch_frame/datasets/amazon_fine_food_reviews.py
torch_frame/datasets/amphibians.py
torch_frame/datasets/bank_marketing.py
torch_frame/datasets/data_frame_benchmark.py
torch_frame/datasets/data_frame_text_benchmark.py
torch_frame/datasets/diamond_images.py
torch_frame/datasets/dota2.py
torch_frame/datasets/fake.py
torch_frame/datasets/forest_cover_type.py
torch_frame/datasets/huggingface_dataset.py
torch_frame/datasets/kdd_census_income.py
torch_frame/datasets/mercari.py
torch_frame/datasets/movielens_1m.py
torch_frame/datasets/multimodal_text_benchmark.py
torch_frame/datasets/mushroom.py
torch_frame/datasets/poker_hand.py
torch_frame/datasets/tabular_benchmark.py
torch_frame/datasets/titanic.py
torch_frame/datasets/yandex.py
torch_frame/gbdt/__init__.py
torch_frame/gbdt/gbdt.py
torch_frame/gbdt/tuned_catboost.py
torch_frame/gbdt/tuned_lightgbm.py
torch_frame/gbdt/tuned_xgboost.py
torch_frame/nn/__init__.py
torch_frame/nn/base.py
torch_frame/nn/conv/__init__.py
torch_frame/nn/conv/excelformer_conv.py
torch_frame/nn/conv/ft_transformer_convs.py
torch_frame/nn/conv/tab_transformer_conv.py
torch_frame/nn/conv/table_conv.py
torch_frame/nn/conv/trompt_conv.py
torch_frame/nn/decoder/__init__.py
torch_frame/nn/decoder/decoder.py
torch_frame/nn/decoder/excelformer_decoder.py
torch_frame/nn/decoder/trompt_decoder.py
torch_frame/nn/encoder/__init__.py
pytorch_frame-0.2.4.dist-info/WHEEL
pytorch_frame-0.2.4.dist-info/METADATA
pytorch_frame-0.2.4.dist-info/RECORD
