Metadata-Version: 2.3
Name: pytorch-frame
Version: 0.2.4
Summary: Tabular Deep Learning Library for PyTorch
Keywords: deep-learning,pytorch,tabular-learning,data-frame
Author-email: PyG Team <team@pyg.org>
Requires-Python: >=3.9
Classifier: Development Status :: 4 - Beta
Classifier: License :: OSI Approved :: MIT License
Classifier: Programming Language :: Python
Classifier: Programming Language :: Python :: 3.9
Classifier: Programming Language :: Python :: 3.10
Classifier: Programming Language :: Python :: 3.11
Classifier: Programming Language :: Python :: 3 :: Only
Requires-Dist: numpy
Requires-Dist: pandas
Requires-Dist: torch
Requires-Dist: tqdm
Requires-Dist: pyarrow
Requires-Dist: Pillow
Requires-Dist: pytorch-frame[test] ; extra == "dev"
Requires-Dist: pre-commit ; extra == "dev"
Requires-Dist: scikit-learn ; extra == "full"
Requires-Dist: xgboost>=1.7.0, <2.0.0 ; extra == "full"
Requires-Dist: optuna>=3.0.0 ; extra == "full"
Requires-Dist: optuna-integration ; extra == "full"
Requires-Dist: mpmath==1.3.0 ; extra == "full"
Requires-Dist: catboost ; extra == "full"
Requires-Dist: lightgbm ; extra == "full"
Requires-Dist: datasets ; extra == "full"
Requires-Dist: torchmetrics ; extra == "full"
Requires-Dist: pytest ; extra == "test"
Requires-Dist: pytest-cov ; extra == "test"
Requires-Dist: mypy ; extra == "test"
Project-URL: changelog, https://github.com/pyg-team/pytorch-frame/blob/master/CHANGELOG.md
Project-URL: documentation, https://pytorch-frame.readthedocs.io
Project-URL: homepage, https://pyg.org
Project-URL: repository, https://github.com/pyg-team/pytorch-frame.git
Provides-Extra: dev
Provides-Extra: full
Provides-Extra: test
